{
    "XQTAeHrfKcDR": {
        "code": "/*\n  @title   Test First Day\n  @by      Ido\n  @album   None\n  @license LGPL\n  @url     https://www.tiktok.com/@puddinggorrila\n*/\n\nsetGainCurve(x => Math.pow(x, 2))\n$aa: s(\"bd sd [~ bd] sd, hh*8\").compressor(\"-20:20:10:.002:.02\")\n   .postgain(slider(0.741,0,1))\n   .gain(slider(1,0,1,1))\n   .orbit(1)\n\n$: note(\"e4 e4 e4 ~ c4 e4 g4 g ~*4 c4 g e e\").sound(\"piano\").slow(slider(12, 1, 16, 1))\n$: s(\"bd(5,8)\").whenKey(\"Control:j\", x => x.segment(16).color(\"red\")).whenKey(\"Control:i\", x => x.fast(2).color(\"blue\"))\n$: note(\"c d e g\").palindrome()\n\n/*\n$: note(\"c3!8\".add(\"{0 0 12 0 7 5 3}%8\"))\n  .s(\"bytebeat:2\")\n  .bbst(\n    \"<3 1>\".mul(slider(10,1,10,1).mul(10000)))\n  .color(\"red\")j\n  ._scope()\n\n*/\n/*\n$: n(\n  accelerationX.segment(4).range(\n    slider(20,0,20,1),\n    slider(20,0,20,1)\n  )\n).scale(\"C:minor\")._scope()\n*/\n\n/*\nsamples({ rhodes: 'https://cdn.freesound.org/previews/132/132051_316502-lq.mp3' })\n$1: s(\"rhodes/2\").fit().orbit(2)\n*/\n/*\nstack(\n  s(\"hh*3\").delay(.5).delaytime(.25).orbit(1),\n  s(\"~ sd ~ sd\").delay(.5).delaytime(.125).orbit(4),\n  s(\"~ sd ~ hh\").orbit(1)\n)\n*/\n//samples('github:switchangel/pad')\n//s(\"swpad:0\").scrub(\"{0.1!2 .25@5 0.7!2 <0.8:1.5>}%8\")\n//s(\"swpad:0\").scrub(\"{0.1!2 .25@5 0.7!2 <0.8:1.5>}%8\")",
        "created_at": 1762886424096,
        "id": "XQTAeHrfKcDR",
        "collection": "user"
    },
    "DDGRisHGGEA8": {
        "code": "/*\n  @title   Drums Test\n  @by      Ido\n  @album   None\n  @license LGPL\n  @url     https://www.tiktok.com/@puddinggorrila\n*/\n\ns(\"bd*2 hh*3, [sd bd]*2 perc\").zoom(0.25, 0.75)",
        "created_at": 1762972605212,
        "id": "DDGRisHGGEA8",
        "collection": "user"
    },
    "dKP1q23ylUc3": {
        "code": "/*\n  @title   Pending Name\n  @by      Ido\n  @album   None\n  @license LGPL\n  @url     https://www.tiktok.com/@puddinggorrila\n*/\n\nnote(\"0 1 2 3 4 5 6 7\".scale(\"C:ritusen\")).sound(\"folkharp\")\n   .shrink(\"2 -1\").pace(10).color(\"red\")",
        "created_at": 1762974519054,
        "id": "dKP1q23ylUc3",
        "collection": "user"
    },
    "bF_EJ9Gxze4u": {
        "code": "/*\n  @title   Pending name\n  @by      Ido\n  @album   None\n  @license LGPL\n  @url     https://www.tiktok.com/@puddinggorrila\n*/\n\nsetGainCurve(x => Math.pow(x, 2))\n// $aa: s(\"bd sd [~ bd] sd, hh*8\").compressor(\"-20:20:10:.002:.02\")\n   // .postgain(slider(0.741,0,1))\n   // .gain(slider(0,0,1,1))\n   // .orbit(1)\n\n//$: note(\"e4 e4 e4 ~ c4 e4 g4 g ~*4 c4 g e e\").sound(\"piano\").slow(slider(12, 1, 16, 1))\n//$: s(\"bd(5,8)\").whenKey(\"Control:j\", x => x.segment(16).color(\"red\")).whenKey(\"Control:i\", x => x.fast(2).color(\"blue\"))\n//$: note(\"c d e g\").palindrome()\n$: note(pure(0.1).mul(2).pow(4))\n\n/*\n$: note(\"c3!8\".add(\"{0 0 12 0 7 5 3}%8\"))\n  .s(\"bytebeat:2\")\n  .bbst(\n    \"<3 1>\".mul(slider(10,1,10,1).mul(10000)))\n  .color(\"red\")j\n  ._scope()\n\n*/\n/*\n$: n(\n  accelerationX.segment(4).range(\n    slider(20,0,20,1),\n    slider(20,0,20,1)\n  )\n).scale(\"C:minor\")._scope()\n*/\n\n/*\nsamples({ rhodes: 'https://cdn.freesound.org/previews/132/132051_316502-lq.mp3' })\n$1: s(\"rhodes/2\").fit().orbit(2)\n*/\n/*\nstack(\n  s(\"hh*3\").delay(.5).delaytime(.25).orbit(1),\n  s(\"~ sd ~ sd\").delay(.5).delaytime(.125).orbit(4),\n  s(\"~ sd ~ hh\").orbit(1)\n)\n*/\n//samples('github:switchangel/pad')\n//s(\"swpad:0\").scrub(\"{0.1!2 .25@5 0.7!2 <0.8:1.5>}%8\")\n//s(\"swpad:0\").scrub(\"{0.1!2 .25@5 0.7!2 <0.8:1.5>}%8\")",
        "created_at": 1763384165819,
        "id": "bF_EJ9Gxze4u",
        "collection": "user"
    },
    "ktXHhmVvSZ5k": {
        "code": "/*\n  @title   Pending name\n  @by      Ido\n  @album   None\n  @license LGPL\n  @url     https://www.tiktok.com/@puddinggorrila\n*/\n\n//setGainCurve(x => Math.pow(x, 2))\nsetCps(140/60/4)\n//register('rlpf', (x, pat) => pat.lpf(pure(x).mul(12).pow(4)))\n\n$aa: s(\"hh*8\").compressor(\"-20:20:10:.002:.02\").postgain(slider(0,0,1))\n   // .postgain(slider(0.741,0,1))\n   // .gain(slider(0,0,1,1))\n   // .orbit(1)\na: s(\"cp!16?\".degradeBy(.5))._punchcard().postgain(slider(0, 0, 1))\nb: n(\"1 4 9 10\").slow(\"1 2 1\").sound(\"conga\").postgain(slider(0.936,0,1))._punchcard({labels:1})\n//$: note(\"e4 e4 e4 ~ c4 e4 g4 g ~*4 c4 g e e\").sound(\"piano\").slow(slider(12, 1, 16, 1))\n//$: n(irand(8).segment(4)).scale(\"c:pentatonic\")._punchcard()\n//$: note(\"c d e g\").palindrome()\n//$: note(\"e f\")._scope()\n\n/*\n$: note(\"c3!8\".add(\"{0 0 12 0 7 5 3}%8\"))\n  .s(\"bytebeat:2\")\n  .bbst(\n    \"<3 1>\".mul(slider(10,1,10,1).mul(10000)))\n  .color(\"red\")j\n  ._scope()\n\n*/\n/*\n$: n(\n  accelerationX.segment(4).range(\n    slider(20,0,20,1),\n    slider(20,0,20,1)\n  )\n).scale(\"C:minor\")._scope()\n*/\n\n/*\nsamples({ rhodes: 'https://cdn.freesound.org/previews/132/132051_316502-lq.mp3' })\n$1: s(\"rhodes/2\").fit().orbit(2)\n*/\n/*\nstack(\n  s(\"hh*3\").delay(.5).delaytime(.25).orbit(1),\n  s(\"~ sd ~ sd\").delay(.5).delaytime(.125).orbit(4),\n  s(\"~ sd ~ hh\").orbit(1)\n)\n*/\n//samples('github:switchangel/pad')\n//s(\"swpad:0\").scrub(\"{0.1!2 .25@5 0.7!2 <0.8:1.5>}%8\")\n//s(\"swpad:0\").scrub(\"{0.1!2 .25@5 0.7!2 <0.8:1.5>}%8\")",
        "created_at": 1763392049232,
        "id": "ktXHhmVvSZ5k",
        "collection": "user"
    },
    "v_WCxVqK9ARu": {
        "code": "/*\n  @title   Array (Lil Data Edit)\n  @by      DJ_Dave\n  @album   Intercell [The Live Code Edits]\n  @license CC BY-NC-SA (code)\n  @url     https://instagram.com/lildata.music\n*/\n\n// load sample pack...\nsamples({\n  build_bass:  ['snd/bass/build_0.mp3', 'snd/bass/build_1.mp3', 'snd/bass/build_2.mp3', 'snd/bass/build_3.mp3'],\n  build_synth: ['snd/synth/build_0.mp3','snd/synth/build_1.mp3','snd/synth/build_2.mp3','snd/synth/build_3.mp3'],\n  build_vox:   ['snd/vox/build_0.mp3',  'snd/vox/build_1.mp3',  'snd/vox/build_2.mp3',  'snd/vox/build_3.mp3'],\n  drop_vox:    ['snd/vox/drop_0.mp3',   'snd/vox/drop_1.mp3',   'snd/vox/drop_2.mp3',   'snd/vox/drop_3.mp3',\n                'snd/vox/drop_4.mp3',   'snd/vox/drop_5.mp3',   'snd/vox/drop_6.mp3',   'snd/vox/drop_7.mp3',\n                'snd/vox/drop_8.mp3'],\n  verse_vox:   ['snd/vox/verse_0.mp3',  'snd/vox/verse_1.mp3',  'snd/vox/verse_2.mp3',  'snd/vox/verse_3.mp3',\n                'snd/vox/verse_4.mp3',  'snd/vox/verse_5.mp3',  'snd/vox/verse_6.mp3',  'snd/vox/verse_7.mp3',\n                'snd/vox/verse_8.mp3'],\n  sub:    ['snd/bass/sub_0.mp3',  'snd/bass/sub_1.mp3',  'snd/bass/sub_2.mp3'],\n  bass:   ['snd/bass/bass_0.mp3', 'snd/bass/bass_1.mp3', 'snd/bass/bass_2.mp3'],\n  kick:    'snd/perc/kick.mp3',\n  sn:      'snd/perc/sn.mp3',\n  cp:     ['snd/perc/cp.mp3', 'snd/perc/cp2.mp3'],\n  tom:     'snd/perc/tom.mp3',\n  hc:      'snd/perc/hc.mp3',\n  shaker:  'snd/perc/shaker.mp3',\n  break:   'snd/perc/break.mp3',\n  guitar: ['snd/perc/guit1.mp3', 'snd/perc/guit2.mp3'],\n}, 'github:lil-data/dj_dave-array_remix/main/');\n\n// hack: https://github.com/tidalcycles/strudel/issues/119\nconst loopAx = register('loopAx', \n  (l, pat) => pat.loopAt(l).chop(l*8).legato(1).mul(speed(0.99))\n);\nconst setbpm = t => setcps(t/4/60)\n\nsetbpm(140)\n\n/*\n  So I try...\n*/\nlet build = stack(\n  n(\"<0 1 2 3>\").s(\"bass\").bank(\"build\").loopAx(4),\n  n(\"<0 1 2 3>\").s(\"synth\").bank(\"build\").loopAx(4),\n  n(\"<0 1 2 3>\").s(\"vox\").bank(\"build\").loopAx(4),\n)\n\nlet predrop = n(\"0\").s(\"vox\").bank(\"drop\").loopAx(2)\n\n/*\n  I swear to god I always thought in the end I’d get you back\n  Now every day I see your face you give me a heart attack\n*/\nlet drop = stack(\n  n(run(8).add(1).slow(8)).s(\"vox\").bank(\"drop\").loopAx(2)\n    .mask(cat([\n      \"1!6 0!2\",         \"1!3 0 1!2 0 1\",\n      \"1!6 0!2\",         \"1\",\n      \"0 1!2 0 1!2 0 1\", \"1\",\n      \"0 1 0 1 0 1 0!2\", \"1!7 0\"\n    ]).slow(16)),\n  stack(\n    stack(\n      s(\"sub(5,16)\").end(0.95).mask(\"[0 1]/8\"),\n      s(\"kick(5,16)\"),\n      s(\"cp(5,16)\").late(3/32),\n      s(\"tom(5,16)\").end(0.95).late(4/32)\n    ).slow(2)\n    .note(\"[0 1]/4\".add(36))\n    .mask(cat([\n      \"[1 [1 0!7]]\",\n      \"[1 [1 0] 0 1 [1 0] 0 1!2]\",\n      \"[1 [1 0]]\",\n      \"[1 [1 0] 0 1 [1 0] 0!3]\", \n    ]).slow(8))),\n  stack(\n    s(\"guitar\").n(\"[0 1]/8\").loopAx(0.5)\n      .mask(\"0!3 1 0!11 1\".slow(8)),\n    s(\"break\").loopAx(0.5).mask(\"0!15 1\".slow(8)),\n    s(\"hc*4\").ply(cat([\n      \"[~!6 2!7 ~!3]\",\n      \"[[9 ~] [6 ~]] 3 3 2\",\n      \"2 3 [[6 ~] [9 ~]] ~\",\n      \"[2 3] ~!3\"\n    ]).slow(8))).mask(\"[1 0]/16\"),\n  stack(\n    s(\"shaker\").loopAx(2),\n    s(\"break\").loopAx(0.5).mask(\"[0!3 [0 1]] [0 [0 1] 0!2]\".slow(8)),\n    s(\"cp:1\").struct(\"[~!7 x] ~\".slow(4)).gain(0.6),\n    s(\"sn\").struct(cat([\n      \"~ x ~ [~ x] [~!15 x] [x ~ ~ x] [~ x ~ x] x\",\n      \"~ x ~ [~*2 x*2]!2 [~ x ~ ~] ~ [~*2 x*2]\",\n      \"~ x ~ [~ x] [~!15 x] x ~ ~\",\n      \"~ x ~ [~*2 x*2]!2 ~!3\",\n    ]).slow(8))\n  ).mask(\"[0 1]/16\"),\n)\n\n/*\n  Where’d you go?\n  I saw your face and moments later I was on the floor \n  (I swear to god I always thought in the end I’d get you back)\n  Putting the pieces together but still you needed more\n  It’s still so hard to see you cry I just want answers for\n  What else I could possibly give you now it’s all for show\n  Where’d you go?\n  Pieces together but still you\n  On the floor / needed more\n  Hard to see you cry I just want\n  Answers for / wherе’d you go?\n  Face and moments later I was\n  On thе floor, where’d you go? Where’d you go? Where’d you go?\n*/\nlet verse = stack(\n  n(run(8).slow(8)).s(\"vox\").bank(\"verse\").loopAx(2),\n  s(\"bass:[0 0 [0 1] [1 2]]/8, sub:[1 2]/8\")\n    .note(cat([\n      \"[0!7 7] [1!3 5] [0!7 12] [7 4 5 [5 12]]\",\n      \"[0 [0 .. 7]] [1!3 5] [0!7 12] [7 4 5 [5 2]]\"\n    ]).slow(8)).add(36)\n    .struct(cat([\n      \"x@3!5 x x@3!5 x\",\n      \"x@3!5 x x@3!5 x\", \n      \"[[x@3 x@3 x@2] [x*8]] [x@3!5 x]\",\n      \"x@3!5 x x@3!5 x\",\n    ]).slow(8))\n    .mask(cat([\"1\",\"1\",\"1 0 0 [0 1]\",\"1\",\"1\",\"1\",\"1\",\"1\"]).slow(8))\n    .slow(2)\n)\n\nlet postverse = stack(\n  n(\"[8 ~]/2\").s(\"vox\").bank(\"verse\").loopAx(2),\n  n(\"[~ 0]/2\").s(\"vox\").bank(\"drop\").loopAx(2),\n  s(\"bass:2, sub:2\").note(\"[2 5]\").add(36)\n    .struct(\"[~@2 x@3!10]\")\n    .mask(\"[1!7 0]\")\n    .slow(4)\n)\n\narrange(\n  [16, build],\n  [2, predrop],\n  [16, drop],\n  [16, verse],\n  [4, postverse]\n).fontFamily(\"x3270\")\n  .theme(\"[teletext algoboy terminal abcdef androidstudio atomone aura bespin darcula dracula duotoneDark eclipse githubDark gruvboxDark materialDark nord okaidia solarizedDark sublime tokyoNight tokyoNightStorm vscodeDark xcodeDark bbedit duotoneLight githubLight gruvboxLight materialLight noctisLilac solarizedLight tokyoNightDay xcodeLight]/54\")\n  .color(\"[fuschia [aquamarine dodgerblue] [hotpink] blueviolet deeppink [cornsilk indigo] crimson cyan]/27\")\n  ._punchcard({fold:1,flipTime:1})\n\n/*\n▓▓█▓▓█▓█▓▓▓▓▓▓▓▓████▓▓▓█▓█▓▓▓▓▓▓▓▓▓▒▓▒▒▒▒▓███████▓▓▓▓▓▓▓▓▓▒▒▒▒▒▒▓▓▓▓▓▓▓▓▓▒▓▒▒▒▒░░░░░░░░░░░\n▓▓▓▓██▓█▓▓▓▓▓▓▓▓███▓▓▓▓▓▓█▓▓▓▓▓▓▓▓▒▒▓▒▒░▒▓████████▓▓▓▓▓▒▒▓▒▒▒▒▒▒▒▒▓▓▓▓▓▓▓▒▓▓▒▒▒▒░░░░░░░░░░\n▓▓▓██▓██▓▓▓▓▓▓████▓▓▓▓▓▓▓▓▓▓▓▓▓▓▓▒▒▒▒▒░░▓██████████████▓▓▓▓▒▒▒▒▒▒▓▓▓▓▓▓▓▓▒▓▓▓▒▒▒░░░░░░░░░░\n▓▓█▓▓██▓▓▓▓▓▓▓█▓▓▓▓▓▓▓▓▓▓▓▓▓▓▓▓▒▒▒▒▓▒▒░▒▓█████████████████▓▓▓▓▒▒▓▓▓▓▓▓▓▓▓▒▓▓▓▓▒▒▒▒░░░░░░░░\n▓█▓▓██▓▓▓▓▓▓▓██▓▓▓▓▓▓▓▓▓▓▓▓▓▓▓▓▒▒▒▒▓▒░░▒████████████████▓▓███▓▓▓▓▓▓▓▓▓▓▓▓▒▓▓▓▓▓▓▒▒▒▒░░░░░░\n█▓▓██▓▓▓▓▓▒▓███▓▓▓▓▓▓▓▓▓▓▓▓▓▓▓▒▒▒▒▒▒░░░▒████████████████▓▓▓▓██▓▒▒▓▓▓▓▓▓█▓░▓█▓▓▓▓▓▒▒▒▒░░░░░\n█▓██▓▓▓▓▓▓▓███▓▓▓▓▓▓▓▓▓▓▓▓▓▓▓▒▒▒▒▒▒▒░░▒███████████████▓▓▓▓▓▒▒▒▓▓▒▓▓▓▓▓▓█▓▒▓██▓▓▓▓▒▒▒▒░░░░░\n███▓▓▓▓▓▓▓▓▓█▓▓▓▒▓▓▓▓▓▓▓▓▓▓▓▒▒▒▒▒▒▒░░░▒█████████████▓▓▓▓▒▒▒▒▒░▒▓▓▒▓▓▓▓██▒▒████▓▓▓▓▒▒▒░░░░░\n███▓▓▓▓▓▓▓▓▓▓▓▓▒▒▓▓▓▓▓▓▓▓▓▓▒▒▒▒▒▒▒░░░░▓███████████▓▓▓▓▓▓▓▓▓▓▒▒▒▓▓▓▓▓████▒▓████▓▓▓▓▒▒▒░░░░░\n█▓▓▓▓▓▓█▓▓▓▓▓▓▒▓▓▓▓▓▓▓▓▓▓▓▓▒▒▒▒▒▒░░░░▒▓█▓███████████▓▓▓▓▓▓▓▒▒░▒▓█▓▓▓███▓▒▓████▓▓▓▓▓▒▒░░░░░\n█▓▓▓▓███▓▓▓▓▒▒▒▓▓▓▓▓▓▓▓▓▒▓▓▒▒▒▒▒▒░░░░▒▓▓▓▓██████▓▓██▓▓▓▓▓▒▒▒▒▒▒▓▓█▓▓███▓▒█████▓▓▓▓▓▒▒░░░░░\n██▓▓████▓▓▓▒▒▒▓▓▓▓▓▓▓▓▓▓▒▒▒▒▒▒▒▒░░░░░▓▓▓▓▓▓▓▓▓██▓▓▓█▓▓▓▓▓▒▒▒▒▒░▒▒▓▓▓▓▓▓▒▒██████▓▓▓▓▓▒▒░░░░\n█▓██████▓▓▒▒▒▓▓▓▓▓▓▓▓▓▓▒▒▒▒▒▒▒▒▒░░░░▒▓▓▓▓▓▓▓▓▓▓▓▓▓▓▓▓▓▓▓▓▓▒▒▒▒▒▒▒▒▓█▓▓▓▒▓▓█████▓▓▓▓▓▓▒▒░░░\n███████▓▓▒▒▒▓▓▓▓▓▓▓▓▓▓▒▒▒▓▒▒▒▒▒░░░▒▒▒▓▓▓▓▓▓▓▓▓▓▓▓▓▓▓▓▓▓▓▓▒▒▒▒▒▒▒▒▒▒▓▓▓▓▒▓▓▓█▓▓▓▓▓▓▓▓▓▓▒▒░░\n██████▓▓▒▒▓▓▓▓▓▓▓▓▓▓▓▓▒▒▓▓▒▒▒▒▒░░▒▒▒▒▓▓▓▓▓▓▓▒▒▒▒▒▒▒▒▒▒▒▒▒▒▒▒▒▒▒▒▒▒▒▓▓▓▒▒▓▓▓▓▓▓▓▓▓▓▓▓▓▓▓▒▒░\n█████▓▓▒▒▓▓▓▓▓▓▓▓▓▓▓▓▓▒▒▓▓▒▒▒▒▒░▒▒▒▒▓▓▓▓▓▓▓▓▒▒▒▒▒▒▒▒▒▒▒▒▒▒▒▒▒▒▒▒▒▒▒▓▓▓▒▒▓▓▓▓▓▓▓▓▓▓▓▓▓▓▓▓▓▒\n█████▓▒▒▓▓▓▓▓▓▓▓▓▓▓▓▓▓▒▓▓▓▒▒▒▒░░▒▒▒▒▓▓▓▓▓▓▓▓▓▓▒▒▒▒▒▒▒▒▒▒▒▒▒▒▒▒▒▒▒▒▓▓▓▓▒▒▓▓▓▓▓▓▓▓▓▓▓▓▓▓▓▓▓▓\n████▓▒▒▓▓▓▓▓▓▓▓▓▓▓▓▓▓▓▓▓▓▒▒▒▒▒▒▒▒▒▓▓▓▓▓▓▓▓▓▓▓▓▓▓▒▒▒▒▒▒▒▒▒▒▒▒▒▒▒▒▒▒▓▓▓▓▒▒▓▓▓▓▓▓▓▓▓▓▓▓▓▓▓▓▓▓\n███▓▒▒▓▓▓▓▓▓▓▓▒▓▓▓▓▓▓▓▓▓▒▒▒▒▒▒▒▒▓▓▓▓▓▓▓▓▓▓▓▓▓▓▓▓▓▒▒▒▒▒▒▒▒▒▒▒▒▒▒▒▒▒▓▓▓▒▒▒▓▓▓▓▓▓▓▓▓▓▓▓▓▓▓▓▓▓\n██▓▒▒▓▓▓▓▓▓▓▓▓▒▒▓▓▓▓▒▓▓▒▒▒▒▒▒▒▒▓▓▓▓▓▓▓▓▓▓▓▓▓▓▓▓▓▓▓▓▓▒▒▒▒▒▒▒▒▒▒▒▒▒▒▒▓▓▒▒▒▓▓▓▓▓▓▓▓▓▓▓▓▓▓▓▓▓▓\n██▓▒▒▓▓▓▓▓▓▓▓▓▓▒▒▓▓▓▓▓▒▓▒▒▒▒▓▓▓▓▓█▓▓▓▓▓▓▓▓▓▓▓▓▓▓▓▓▓▓▓▒▒▒▒▒▒▒▒▒▒▒▒▒▒▓▓▒▒▒▓▓▓▓▓▓▓▓▓▓▓▓▓▓▓▓▓▓\n█▓▒▒▓▓▓▓▓▓▓▓▓▓▓▒▒▓▓▓▒▒▓▒▒▒▓▓▓▓▓▓█████▓▓▓▓▓▓▓▓▓▓▓▓▓▓▓▓▓▓▒▒▒▒▒▒▒▒▒▒▒▒▓▓▒▒▒▓▓▓█████▓▓▓▓▓▓▓▓▓▓\n▓▓▒▓▓▓▓▓▓▓▓▓▓▓▓▓▒▒▒▓▒▒▒▒▓▓▓▓▓▓▓████████▓▓▓▓▓▓▓▓▓▓▓▓▓▓▓▓▓▓▓▒▒▒▒▒▒▒▒▒▓▓▒▒▒▓██████▓▓▓▓▓▓▓▓▓▓▓\n▓▒▒▓▓▓▓▓▓▓▓▓▓▓▓▓▒▒▒▓▓▒▒▓▓█▓▓▓▓▓███████████▓▓▓▓▓▓▓▓▓▓▓▓▓▓▓▓▓▓▓▒▒▒▒▒▓▓▓▒▒▒▓████▓▓▓▓▓▓▓▓▓████\n▓▒▓▓▓▓▓▓▓▓▓▓▓▓▓▓▒▒▒▒▓▓▓▓▓▓▓▓▓▓▓█████████████▓▓▓▓▓▓▓▓▓▓▓▓▓▓▓▓▓▓▒▒▓▓▓▓▓▓▒▒▓████▓▓▓▓▓▓▓▓█████\n▒▒▓▓▓▓▓▓▓▓▓▓▓▓▓▓▓▒▒▒▓▓▓▓▓██▓▓▓▓▓███████████████▓▓▓▓▓▓▓▓▓▓▓▓▓▓▓▓▓▓▓▓▓▓▓▒▒▓█████████████████\n▒▒▓▓▓▓▓▓▓▓▓▓▓▓▒▓▓▓▓▒▒▓▓▓▓██▓▓▓▓▓████████████████▓▓▓▓▓▓▓▓▓▓▓▓▓▓▓▓▓▓▓▓▓▓▒▒▓█████████████████\n▒▓▓▓▓▓▓▓▓▓▓▓▓▒▓▓▓▓▓▓▓▒▓▓▓▓█▓▓▓▓▓▓████████████████▓▓▓▓▓▓▓▓▓▓▓▓▓▓▓▒▓▓▓▓▓▓▓▓█████████████████\n▒▓▓▓▓▓▓▓▓▓▓▓▓▓▓▓▓███▓▓▓▓▓▓███▓▓▓▓▓████████████████▓▓▓▓▓▓▓▓▓▓▓▓▓▓▒▒▒▓▓▓▓▒▒█████████████████\n▒▓▓▓▓▓▓▓▓▓▓▓▓▓▓▓█████▓▓▓▓▓▓██▓▓▓▓▓██████████████▓▓▓▓▓▓▓▓▓▓▓▓▓▓▓▓▒▒▒▒▓▓▓▒▒▓████████████████\n▒▓▓▓▓▓▓▓▓▓▓▓▓▓▓▓██████▓▓▓▓▓▓█▓▓▓██▓████▓▓██████▓▓▓▓▓▓▓▓▓▓▓▓▓▓▓▓▓▒▒▒▒▓▓▓▒▒▒▓███████████████\n▒▓▓▓▓▓▓▓▓▓▓▓▓█▓████████▓▓▓▓▓▓▓▓▓▓███████▓▓██████▓▓▓▓▓▓▓▓▓▓▓▓▓▓▓▓▓▓▓▓▓▓▓▒▒▒▓▓▓▓▓▓███████▓▓█\n▓▓▓▓▓▓▓▓▓▓▓▓██▓█████████▓▓▓▓▓█▓▓▓████████▓▓██████▓▓▓▓▓▓▓▓▓▓▓▓▓▓▓▓▓▓▓▓▓▓▓▒▒▒▓▓▓▓▓▓▓▓▓▓▓▓▒▒▒\n▒▓▓▓▓▓▓▓▓▓███████████████▓▓▒▓▓▓▓▓█████████▓▓█████▓▓▓▓▓▓▓▓▓▓▓▓▓▓▓▓▓▓▓▓▓▓▓▒▒▒▒▓▓▓▓▓▓▓▓▓▒▒▒░░\n▒▓▓▓▓▓▓▓▓█████████████████▓▓▒▓▓▓▓▓████████▓▓█████▓▓▓▓▓▓▓▓▓▓▓▓▓▓▓▓▓▓▓▓▓▓▓▓▒▒▒▓▓▓▓▓▓▓▓▒▒▒▒░░\n▒▓▓▓▓▒▓▓███████████████████▓▓▓▓▓▓▓█████████▓▓█████▓▓▓▓▓▓▓▓▓▓▓▓▓▓▓▓▓▓▓▓▓▓▓▓▒▒▒▓▓▓▓▓▓▓▓▒▒▒▒░\n▒▓▓▓▓▓▓█████████████████████▓▓▒▓▓▓▓▓███████▓▓████▓▓▓▓▓▓▓▓▓▓▓▓▓▓▓▓▓▓▓▓▓▓▓▓▓▓▒░▒▓▓▓▓▓▓▓▓▒▒▒▒\n▒▓▓▓▒▓██████▓████████████████▓▓▒▒▓▓▓███████▓▓██████▓▓▓▓▓▓▓▓▓▓▓▓▓▓▓▓▓▓▓▓▓▓▓▓▒▒▒▒▓▓▓▓▓▓▒▒▒▒▓\n▒▓▓▒▓▓████████████████████████▓▓▒▒▓▓███████▓██████████▓▓▓▓▓▓▓▓▓▓▓▓▓▓▓▓▓▓▓▓▓▓▒▒▓▓▓▓▓▓▓▓▓▓▓▓\n▒▒▓▓▓██████████████████████████▓▓▒▒▓▓██████▓▓██████████▓▓▓▓▓▓▓▓▓▓▓▓▓████████▒▓█▓▓▓██████▓▓\n▒▒▓▓▓███████████████████████████▓▓▒▒▓▓████████████████▓▓▓▓▓▓▓▓▓▓▓▓██████████▓▓███▓▓███████\n▒▒▓▓█████████████████████████████▓▓▒▒▓▓▓███████████████▓▓▓▓▓▓▓▓▓▓████████████▒▓████▓▓▓▓▓▓▓\n▒▒▒▓█████████████████████████████▓▓▓▒▒▓▓▓▓██████████████▓▓▓▓▓▓▓▓▓▓▓▓▓▓███▓▓▓▓▒▒▓▓▓▓▒▓▒▒▓▓▓\n▒▒▒▓████████████████████████████▓▓▓▓▓▒▒▓▓▓▓████████████▓▓▓▓▓▓▓▓▓▓▓▓▓▓▓▓▓▓▓▓▓▓▓▒▓▓▓▓▒▒▒▒▒░▒\n*/\n\n\n// @version 1.0",
        "created_at": 1763745545663,
        "id": "v_WCxVqK9ARu",
        "collection": "user"
    },
    "SoLGpG3kZGoO": {
        "code": "/*\n  @title   Pk 1\n  @by      Ido\n  @album   None\n  @license LGPL\n  @url     https://www.tiktok.com/@puddinggorrila\n*/\n\n//setGainCurve(x => Math.pow(x, 2))\nsetCps(140/60/8)\n//$:freq(\"220 275 330 440\")\npk_misterio$:note(`\n  e5 g5 a5 c6  b5 g5 f5 e5,\n    e5 fs5 g5 b5 a5 fs5 e5 d5,\n    d5 f5 g#5 b5 c6 b5 g5 f5,\n    e5 g5 a5 c6 d6 c6 a5 g5\n`).sound(\"gm_acoustic_guitar_steel\").gain(.5).slow(1)\n//register('rlpf', (x, pat) => pat.lpf(pure(x).mul(12).pow(4)))\n//s: s(\"bd bd\").delay(\"0.65:0.25:0.9 0.65:0.125:0.7\")\n\n//$aa: s(\"hh*8\").compressor(\"-20:20:10:.002:.02\").postgain(slider(0,0,1))\n   // .postgain(slider(0.741,0,1))\n   // .gain(slider(0,0,1,1))\n   // .orbit(1)\n//b:s(\"bd*4,hh*8\").cutoff(perlin.range(0,7))\n//a: s(\"cp!16?\".degradeBy(.5))._punchcard().postgain(slider(0, 0, 1))\n//b: n(perlin.range(0,7).segment(4)).slow(\"1 2 1\").sound(\"conga\").postgain(slider(10,0,10))._punchcard({labels:1})\n//$: note(\"e4 e4 e4 ~ c4 e4 g4 g ~*4 c4 g e e\").sound(\"piano\").slow(slider(12, 1, 16, 1))\n//$: n(irand(8).segment(4)).scale(\"c:pentatonic\")._punchcard()\n//$: note(\"c d e g\").palindrome()\n//$: note(\"e f\")._scope()\n\n/*\n$: note(\"c3!8\".add(\"{0 0 12 0 7 5 3}%8\"))\n  .s(\"bytebeat:2\")\n  .bbst(\n    \"<3 1>\".mul(slider(10,1,10,1).mul(10000)))\n  .color(\"red\")j\n  ._scope()\n\n*/\n/*\n$: n(\n  accelerationX.segment(4).range(\n    slider(20,0,20,1),\n    slider(20,0,20,1)\n  )\n).scale(\"C:minor\")._scope()\n*/\n\n/*\nsamples({ rhodes: 'https://cdn.freesound.org/previews/132/132051_316502-lq.mp3' })\n$1: s(\"rhodes/2\").fit().orbit(2)\n*/\n/*\nstack(\n  s(\"hh*3\").delay(.5).delaytime(.25).orbit(1),\n  s(\"~ sd ~ sd\").delay(.5).delaytime(.125).orbit(4),\n  s(\"~ sd ~ hh\").orbit(1)\n)\n*/\n//samples('github:switchangel/pad')\n//s(\"swpad:0\").scrub(\"{0.1!2 .25@5 0.7!2 <0.8:1.5>}%8\")\n//s(\"swpad:0\").scrub(\"{0.1!2 .25@5 0.7!2 <0.8:1.5>}%8\")",
        "created_at": 1763998224072,
        "id": "SoLGpG3kZGoO",
        "collection": "user"
    },
    "eUoD_JgoYVD1": {
        "code": "/*\n  @title   Pk 2\n  @by      Ido\n  @album   None\n  @license LGPL\n  @url     https://www.tiktok.com/@puddinggorrila\n*/\n\n//setGainCurve(x => Math.pow(x, 2))\nsetCps(140/60/8)\n//$:freq(\"220 275 330 440\")\npk_misterio$:note(`\n  e5 g5 a5 c6  b5 g5 f5 e5,\n    e5 fs5 g5 b5 a5 fs5 e5 d5,\n    d5 f5 g#5 b5 c6 b5 g5 f5,\n    e5 g5 a5 c6 d6 c6 a5 g5\n`).sound(\"gm_acoustic_guitar_steel\").gain(.5).slow(1)\n//register('rlpf', (x, pat) => pat.lpf(pure(x).mul(12).pow(4)))\n//s: s(\"bd bd\").delay(\"0.65:0.25:0.9 0.65:0.125:0.7\")\n\n//$aa: s(\"hh*8\").compressor(\"-20:20:10:.002:.02\").postgain(slider(0,0,1))\n   // .postgain(slider(0.741,0,1))\n   // .gain(slider(0,0,1,1))\n   // .orbit(1)\n//b:s(\"bd*4,hh*8\").cutoff(perlin.range(0,7))\n//a: s(\"cp!16?\".degradeBy(.5))._punchcard().postgain(slider(0, 0, 1))\n//b: n(perlin.range(0,7).segment(4)).slow(\"1 2 1\").sound(\"conga\").postgain(slider(10,0,10))._punchcard({labels:1})\n//$: note(\"e4 e4 e4 ~ c4 e4 g4 g ~*4 c4 g e e\").sound(\"piano\").slow(slider(12, 1, 16, 1))\n//$: n(irand(8).segment(4)).scale(\"c:pentatonic\")._punchcard()\n//$: note(\"c d e g\").palindrome()\n//$: note(\"e f\")._scope()\n\n/*\n$: note(\"c3!8\".add(\"{0 0 12 0 7 5 3}%8\"))\n  .s(\"bytebeat:2\")\n  .bbst(\n    \"<3 1>\".mul(slider(10,1,10,1).mul(10000)))\n  .color(\"red\")j\n  ._scope()\n\n*/\n/*\n$: n(\n  accelerationX.segment(4).range(\n    slider(20,0,20,1),\n    slider(20,0,20,1)\n  )\n).scale(\"C:minor\")._scope()\n*/\n\n/*\nsamples({ rhodes: 'https://cdn.freesound.org/previews/132/132051_316502-lq.mp3' })\n$1: s(\"rhodes/2\").fit().orbit(2)\n*/\n/*\nstack(\n  s(\"hh*3\").delay(.5).delaytime(.25).orbit(1),\n  s(\"~ sd ~ sd\").delay(.5).delaytime(.125).orbit(4),\n  s(\"~ sd ~ hh\").orbit(1)\n)\n*/\n//samples('github:switchangel/pad')\n//s(\"swpad:0\").scrub(\"{0.1!2 .25@5 0.7!2 <0.8:1.5>}%8\")\n//s(\"swpad:0\").scrub(\"{0.1!2 .25@5 0.7!2 <0.8:1.5>}%8\")",
        "created_at": 1764265954452,
        "id": "eUoD_JgoYVD1",
        "collection": "user"
    },
    "xvkqGGcSgJoz": {
        "code": "/*\n  @title   Pending Name\n  @by      Ido\n  @album   None\n  @license LGPL\n  @url     https://www.tiktok.com/@puddinggorrila\n*/\n\n$: stack(\n  sound(`bd bd*4`),\n  sound(`rd - hh - cr - oh -`).palindrome().gain(.3),\n  sound(`- mt - ht - lt - sd`).gain(.7),\n  sound(`[sd rim]!4`).sometimesBy(slider(0.235,0,1), x => x.gain(0))\n).bank(\"RolandTR909\")\n  .lpf(slider(1926.4,400,4000))\n  .postgain(slider(0.83,0,10))\n  ._punchcard()\n \n$: stack(\n  n(\"0 1 4 2\").sound(\"jazz\"),\n  n(\"7!4\").sound(\"jazz\")\n    .sometimesBy(slider(0.576,0,1), x => x.gain(0))\n  )\n  .postgain(slider(0.37,0,10))\n  ._punchcard()\n$: stack(\n  note(\"<[c2 c3]*4 [bb1 bb2]*4 [f2 f3]*4 [eb2 eb3]*4>\").delay(.2),\n  note(\"a2 b a4 c\").gain(.2)\n).sound(\"sawtooth\")\n  .lpf(slider(3866.8,400,4000))\n  .postgain(slider(0.13,0,10))\n\n\n",
        "created_at": 1764265975062,
        "id": "xvkqGGcSgJoz",
        "collection": "user"
    },
    "EwVIw9ORL18w": {
        "code": "/*\n  @title   Drums Test\n  @by      Ido\n  @album   None\n  @license LGPL\n  @url     https://www.tiktok.com/@puddinggorrila\n*/\n\n\n\n$: note(\"c2 a2 eb2\")\n.euclid(5,8)\n.s('sawtooth')\n.lpenv(4).lpf(300)\n._pianoroll({ labels: 1 })\n\n$: note(\"<0 1 2!2 3>\".pick([\"g a\", \"e f\", \"f g f g\" , \"g c d\"]))",
        "created_at": 1764594026404,
        "id": "EwVIw9ORL18w",
        "collection": "user"
    },
    "5tctwWkR0IXw": {
        "code": "/*\n  @title   PK 3\n  @by      Ido\n  @album   None\n  @license LGPL\n  @url     https://www.tiktok.com/@puddinggorrila\n*/\n\nsetcpm(180/4)\n\n$chanel_1: stack(\n  note(\"D5  D5  F5  D5   A#4  A4  G4  F4\"),\n  note(`\n    D5  D5  F5  D5   A#4  A4  G4  A#4\n    A4  A4  C5  A4   F4   E4  D4  C4\n  `).slow(2),\n  note(\"A4  A4  C5  A4   F4   E4  D4  F4\")\n).scale(\"D:minor\").gain(.7)._punchcard()\n\n$chanel_2: stack(\n  note(`\n    D2  D2  D2  D2   A#1  A#1 A#1 A#1\n    A2  A2  A2  A2   F2   F2  F2  F2\n    G2  G2  G2  G2   D2   D2  D2  D2\n    A#2 A#2 A#2 A#2  F2   F2  F2  F2\n  `).slow(4)\n).scale(\"D:minor\")._punchcard()",
        "created_at": 1764871826842,
        "id": "5tctwWkR0IXw",
        "collection": "user"
    },
    "UyJ1jgjoczww": {
        "code": "/*\n  @title   PK 4\n  @by      Ido\n  @album   None\n  @license LGPL\n  @url     https://www.tiktok.com/@puddinggorrila\n*/\nsetcpm(180/4)\n\n$chanel_1: stack(\n  note(`\n    F5   F5   F5   F5    Eb5  Eb5  Eb5  Eb5\n    Db5  Db5  Db5  Db5   C5   C5   C5   C5\n    B4   B4   B4   B4    A#4  A#4  A#4  A#4\n  `).slow(3)\n).scale(\"D:minor\").gain(.5)\n\n$chanel_2: stack(\n  note(`\n    F1  -  C2  -   F1  -  C2  -\n    A#1 -  F2  -   A#1 -  F2  -\n    Db2 -  Ab2 -   Db2 -  Ab2 -\n    C2  -  G2  -   C2  -  G2  -\n  `).slow(4)\n)",
        "created_at": 1764872747171,
        "id": "UyJ1jgjoczww",
        "collection": "user"
    },
    "VYwm49jZLLCa": {
        "code": "/*\n  @title   PK 5\n  @by      Ido\n  @album   None\n  @license LGPL\n  @url     https://www.tiktok.com/@puddinggorrila\n*/\n\nsetcpm(180/4)\n\n$: stack(\n  note(`\n    F5   F5   F5   F5  Eb5  Eb5  Eb5  Eb5\n    Db5  Db5  Db5  Db5 C5   C5   C5   C5\n    B4   B4   B4   B4  A#4  A#4  A#4  A#4\n  `).slow(3),\n  note(`<Bb4 C5>!4`)\n).gain()\n\n$: stack(\n  note(`\n    E#4 - Bb - Db - C\n  `)\n)",
        "created_at": 1764876834692,
        "id": "VYwm49jZLLCa",
        "collection": "user"
    }
}